mlops_misis/__init__.py
mlops_misis/config.py
mlops_misis/dataset.py
mlops_misis/modeling/__init__.py
mlops_misis/modeling/train.py
mlops_misis-0.0.3.dist-info/WHEEL
mlops_misis-0.0.3.dist-info/METADATA
mlops_misis-0.0.3.dist-info/RECORD
