Metadata-Version: 2.3
Name: mlops_misis
Version: 0.0.3
Summary: MLOps course MISIS University
Author: Roman Shinkarenko
Requires-Python: ~=3.10
Classifier: Programming Language :: Python :: 3
